pollution_analysis/__init__.py
pollution_analysis/config/model_settings.py
pollution_analysis/main.py
pollution_analysis/src/__init__.py
pollution_analysis/src/flaring_descriptor.py
pollution_analysis/src/flaring_grouper.py
pollution_analysis/src/flaring_loader.py
pollution_analysis/src/flaring_scraper.py
pollution_analysis/src/satellite_loader.py
pollution_analysis/utils/__init__.py
pollution_analysis/utils/utils.py
pollution_analysis-0.1.0.dist-info/WHEEL
pollution_analysis-0.1.0.dist-info/METADATA
pollution_analysis-0.1.0.dist-info/RECORD
