Metadata-Version: 2.1
Name: pollution-analysis
Version: 0.1.0
Summary: 
Author: ChristinaLast
Author-email: christina.last@outlook.com
Requires-Python: >=3.8,<4.0
Classifier: Programming Language :: Python :: 3
Classifier: Programming Language :: Python :: 3.10
Classifier: Programming Language :: Python :: 3.8
Classifier: Programming Language :: Python :: 3.9
Requires-Dist: Shapely (>=1.8.1,<2.0.0)
Requires-Dist: geopandas (>=0.9.0,<0.10.0)
Requires-Dist: ipykernel (>=6.9.1,<7.0.0)
Requires-Dist: joblib (>=1.1.0,<2.0.0)
Requires-Dist: matplotlib (>=3.5.1,<4.0.0)
Requires-Dist: nbformat (>=5.1.3,<6.0.0)
Requires-Dist: open-geo-engine @ git+https://github.com/AQ-AI/open-geo-engine.git@e1242d525db7b20f4675647738f867dd0ad7ead2
Requires-Dist: pandas (>=1.3.5,<2.0.0)
Requires-Dist: plotly (>=5.6.0,<6.0.0)
Requires-Dist: requests (>=2.26.0,<3.0.0)
